scalecodec/__init__.py
scalecodec/base.py
scalecodec/block.py
scalecodec/exceptions.py
scalecodec/metadata.py
scalecodec/types.py
scalecodec/updater.py
scalecodec/type_registry/__init__.py
scalecodec/type_registry/canvas.json
scalecodec/type_registry/default.json
scalecodec/type_registry/development.json
scalecodec/type_registry/kusama.json
scalecodec/type_registry/polkadot.json
scalecodec/type_registry/polymesh.json
scalecodec/type_registry/rococo.json
scalecodec/type_registry/statemine.json
scalecodec/type_registry/statemint.json
scalecodec/type_registry/substrate-node-template.json
scalecodec/type_registry/test.json
scalecodec/type_registry/westend.json
scalecodec/utils/__init__.py
scalecodec/utils/math.py
scalecodec/utils/ss58.py
polymath_scalecodec-4.0.0.dist-info/LICENSE
polymath_scalecodec-4.0.0.dist-info/METADATA
polymath_scalecodec-4.0.0.dist-info/WHEEL
polymath_scalecodec-4.0.0.dist-info/top_level.txt
polymath_scalecodec-4.0.0.dist-info/RECORD
