Metadata-Version: 2.1
Name: polymath-scalecodec
Version: 4.0.0
Summary: Python SCALE Codec Library for Polymesh
Home-page: https://github.com/polymathnetwork/py-scale-codec
Author: Polymath
License: UNKNOWN
Keywords: scale codec polkascan polkadot substrate blockchain polymesh
Platform: UNKNOWN
Classifier: Development Status :: 4 - Beta
Classifier: Intended Audience :: Developers
Classifier: License :: OSI Approved :: Apache Software License
Classifier: Programming Language :: Python :: 3
Classifier: Programming Language :: Python :: 3.6
Classifier: Programming Language :: Python :: 3.7
Classifier: Programming Language :: Python :: 3.8
Classifier: Programming Language :: Python :: 3.9
Requires-Python: >=3.6, <4
Requires-Dist: more-itertools
Requires-Dist: base58 (>=2.0.1)
Requires-Dist: requests (>=2.24.0)
Provides-Extra: test
Requires-Dist: coverage ; extra == 'test'
Requires-Dist: pytest ; extra == 'test'
